{
  "HALProvider": {
    "Other Devices": {
      "Talon FX (v6)[0]": {
        "header": {
          "open": true
        }
      }
    }
  },
  "NTProvider": {
    "types": {
      "/FMSInfo": "FMSInfo",
      "/SmartDashboard/Field": "Field2d"
    }
  },
  "NetworkTables": {
    "Persistent Values": {
      "open": false
    },
    "Retained Values": {
      "open": false
    },
    "transitory": {
      "Robot": {
        "Pose2d##v_/Robot/Pose": {
          "Translation2d##v_translation": {
            "open": true
          },
          "open": true
        },
        "open": true
      }
    }
  }
}
